keller_protocol/__init__.py
keller_protocol/keller_protocol.py
keller_protocol/test_keller_protocol.py
keller_protocol-1.0.22.dist-info/LICENSE
keller_protocol-1.0.22.dist-info/METADATA
keller_protocol-1.0.22.dist-info/WHEEL
keller_protocol-1.0.22.dist-info/top_level.txt
keller_protocol-1.0.22.dist-info/RECORD
