Metadata-Version: 2.1
Name: keller_protocol
Version: 1.0.22
Summary: Python package source for KELLER protocol
Home-page: https://github.com/KELLERAGfuerDruckmesstechnik/keller_protocol_python
Author: Lukas Weber
Author-email: engineering@keller-druck.com
Classifier: Programming Language :: Python :: 3
Classifier: License :: OSI Approved :: MIT License
Classifier: Operating System :: OS Independent
License-File: LICENSE
Requires-Dist: pyserial >=3.5
